cared_cli/__init__.py
cared_cli/_cli.py
cared_cli/_logo.py
cared_cli/_version.py
cared_cli/core.py
cared_cli/py.typed
cared_cli-0.1.0.dist-info/METADATA
cared_cli-0.1.0.dist-info/WHEEL
cared_cli-0.1.0.dist-info/entry_points.txt
cared_cli-0.1.0.dist-info/licenses/LICENSE
cared_cli-0.1.0.dist-info/RECORD
