Metadata-Version: 2.3
Name: cared-cli
Version: 0.1.0
Summary: A command line interface for managing a CaReD server.
Project-URL: Documentation, https://github.com/likat-rostock/cared-cli
Project-URL: GitHub, https://github.com/likat-rostock/cared-cli
Project-URL: Changelog, https://github.com/likat-rostock/cared-cli/releases
Author-email: David Linke <david.linke@catalysis.de>
Maintainer-email: David Linke <david.linke@catalysis.de>
License: Apache 2.0
License-File: LICENSE
Keywords: CaReD,ELN,LIMS,RDM
Classifier: Development Status :: 2 - Pre-Alpha
Classifier: Environment :: Console
Classifier: Intended Audience :: Science/Research
Classifier: License :: OSI Approved :: Apache Software License
Classifier: Operating System :: OS Independent
Classifier: Programming Language :: Python
Classifier: Programming Language :: Python :: 3.10
Classifier: Programming Language :: Python :: 3.11
Classifier: Programming Language :: Python :: 3.12
Requires-Python: >=3.10
Requires-Dist: click>=8.1.7
Provides-Extra: dev
Requires-Dist: coverage; extra == 'dev'
Requires-Dist: duty; extra == 'dev'
Requires-Dist: pytest; extra == 'dev'
Requires-Dist: ruff; extra == 'dev'
Provides-Extra: lint
Requires-Dist: ruff; extra == 'lint'
Provides-Extra: tests
Requires-Dist: coverage; extra == 'tests'
Requires-Dist: pytest; extra == 'tests'
